{"nodes": [{"id": "components_nominalroll_nominalroll", "label": "NominalRoll", "file_type": "code", "source_file": "components/NominalRoll.tsx", "source_location": "line 25", "source_url": null, "captured_at": null, "author": null, "contributor": null}, {"id": "components_nominalroll_getranktype", "label": "getRankType", "file_type": "code", "source_file": "components/NominalRoll.tsx", "source_location": "line 17", "source_url": null, "captured_at": null, "author": null, "contributor": null}, {"id": "components_nominalroll_load", "label": "NominalRoll.load", "file_type": "code", "source_file": "components/NominalRoll.tsx", "source_location": "line 40", "source_url": null, "captured_at": null, "author": null, "contributor": null}, {"id": "components_nominalroll_addsoldier", "label": "NominalRoll.addSoldier", "file_type": "code", "source_file": "components/NominalRoll.tsx", "source_location": "line 52", "source_url": null, "captured_at": null, "author": null, "contributor": null}, {"id": "components_nominalroll_deletesoldier", "label": "NominalRoll.deleteSoldier", "file_type": "code", "source_file": "components/NominalRoll.tsx", "source_location": "line 70", "source_url": null, "captured_at": null, "author": null, "contributor": null}, {"id": "concept_rank_classification", "label": "Military Rank Classification (Officer/WOSPEC/Enlistee)", "file_type": "concept", "source_file": "components/NominalRoll.tsx", "source_location": "line 17", "source_url": null, "captured_at": null, "author": null, "contributor": null}], "edges": [{"source": "components_nominalroll_nominalroll", "target": "lib_supabase_getsupabseclient", "relation": "calls", "confidence": "EXTRACTED", "confidence_score": 1.0, "source_file": "components/NominalRoll.tsx", "source_location": "line 26", "weight": 1.0}, {"source": "components_nominalroll_nominalroll", "target": "lib_supabase_soldier", "relation": "references", "confidence": "EXTRACTED", "confidence_score": 1.0, "source_file": "components/NominalRoll.tsx", "source_location": "line 28", "weight": 1.0}, {"source": "components_nominalroll_nominalroll", "target": "components_nominalroll_getranktype", "relation": "calls", "confidence": "EXTRACTED", "confidence_score": 1.0, "source_file": "components/NominalRoll.tsx", "source_location": "line 79", "weight": 1.0}, {"source": "components_nominalroll_nominalroll", "target": "components_nominalroll_load", "relation": "calls", "confidence": "EXTRACTED", "confidence_score": 1.0, "source_file": "components/NominalRoll.tsx", "source_location": "line 37", "weight": 1.0}, {"source": "components_nominalroll_nominalroll", "target": "components_nominalroll_addsoldier", "relation": "calls", "confidence": "EXTRACTED", "confidence_score": 1.0, "source_file": "components/NominalRoll.tsx", "source_location": "line 96", "weight": 1.0}, {"source": "components_nominalroll_nominalroll", "target": "components_nominalroll_deletesoldier", "relation": "calls", "confidence": "EXTRACTED", "confidence_score": 1.0, "source_file": "components/NominalRoll.tsx", "source_location": "line 189", "weight": 1.0}, {"source": "components_nominalroll_addsoldier", "target": "components_nominalroll_load", "relation": "calls", "confidence": "EXTRACTED", "confidence_score": 1.0, "source_file": "components/NominalRoll.tsx", "source_location": "line 65", "weight": 1.0}, {"source": "components_nominalroll_deletesoldier", "target": "components_nominalroll_load", "relation": "calls", "confidence": "EXTRACTED", "confidence_score": 1.0, "source_file": "components/NominalRoll.tsx", "source_location": "line 73", "weight": 1.0}, {"source": "components_nominalroll_getranktype", "target": "concept_rank_classification", "relation": "implements", "confidence": "INFERRED", "confidence_score": 0.95, "source_file": "components/NominalRoll.tsx", "source_location": "line 17", "weight": 1.0}, {"source": "components_nominalroll_load", "target": "components_paradestate_load", "relation": "semantically_similar_to", "confidence": "INFERRED", "confidence_score": 0.85, "source_file": "components/NominalRoll.tsx", "source_location": "line 40", "weight": 0.85}], "hyperedges": []}